README.md
pyproject.toml
setup.cfg
setup.py
elastic_helper/__init__.py
elastic_helper/es_helper.py
elastic_helper/es_helper_test.py
elastic_helper.egg-info/PKG-INFO
elastic_helper.egg-info/SOURCES.txt
elastic_helper.egg-info/dependency_links.txt
elastic_helper.egg-info/requires.txt
elastic_helper.egg-info/top_level.txt