Metadata-Version: 2.1
Name: elastic-helper
Version: 1.2.4
Summary: Elastic Search to Pandas Dataframe
Home-page: https://github.com/snuids/elastic_helper
Author: snuids
Author-email: snuids@mannekentech.com
License: UNKNOWN
Download-URL: https://github.com/snuids/elastic_helper/archive/1.2.4.tar.gz
Keywords: ElasticSearch,pandas,convert
Platform: UNKNOWN
Classifier: License :: OSI Approved :: GNU General Public License v3 or later (GPLv3+)
